shein_api/__init__.py
shein_api/__version__.py
shein_api/api/__init__.py
shein_api/api/auth.py
shein_api/api/auth_service.py
shein_api/api/base.py
shein_api/api/cargo.py
shein_api/api/feed.py
shein_api/api/finance.py
shein_api/api/goods.py
shein_api/api/material.py
shein_api/api/mdp.py
shein_api/api/mes.py
shein_api/api/order.py
shein_api/api/return_order.py
shein_api/api/shipping.py
shein_api/api/store.py
shein_api/api/warehouse.py
shein_api/base/api_response.py
shein_api/base/base_client.py
shein_api/base/crypto.py
shein_api/base/exceptions.py
shein_api/base/helpers.py
shein_api-0.0.7.dist-info/LICENSE
shein_api-0.0.7.dist-info/METADATA
shein_api-0.0.7.dist-info/WHEEL
shein_api-0.0.7.dist-info/top_level.txt
shein_api-0.0.7.dist-info/RECORD
