Metadata-Version: 2.1
Name: shein-api
Version: 0.0.7
Summary: Python wrapper for the SHEIN API
Home-page: https://github.com/xie7654/shein_api
Author: XIE JUN
Author-email: xie765462425@gmail.com
License: MIT
Platform: UNKNOWN
License-File: LICENSE
Requires-Dist: requests (>=2.26.0)
Requires-Dist: pycryptodome (>=3.11.0)
